src/__init__.py
src/_git.py
src/_gitlab.py
src/_settings.py
src/_utils.py
src/main.py
src/commands/__init__.py
src/commands/groups.py
src/commands/projects.py
src/commands/tree.py
gitlab_dumper-0.1.1.dist-info/LICENSE
gitlab_dumper-0.1.1.dist-info/METADATA
gitlab_dumper-0.1.1.dist-info/WHEEL
gitlab_dumper-0.1.1.dist-info/entry_points.txt
gitlab_dumper-0.1.1.dist-info/top_level.txt
gitlab_dumper-0.1.1.dist-info/RECORD
