Metadata-Version: 2.1
Name: gitlab-dumper
Version: 0.1.1
Summary: CLI tool for dump Gitlab projects
Home-page: https://github.com/akimrx/gitlab-dumper
Author: akimrx
Author-email: akimstrong@yandex.ru
License: MIT
Keywords: gitlab
Platform: osx
Platform: linux
Classifier: Programming Language :: Python :: 3.10
Requires-Python: >=3.10
License-File: LICENSE
Requires-Dist: annotated-types ==0.6.0
Requires-Dist: certifi ==2024.2.2
Requires-Dist: charset-normalizer ==3.3.2
Requires-Dist: click ==8.1.7
Requires-Dist: gitdb ==4.0.11
Requires-Dist: GitPython ==3.1.41
Requires-Dist: idna ==3.6
Requires-Dist: pydantic ==2.6.1
Requires-Dist: pydantic-settings ==2.1.0
Requires-Dist: pydantic-core ==2.16.2
Requires-Dist: python-dotenv ==1.0.1
Requires-Dist: python-gitlab ==4.4.0
Requires-Dist: requests ==2.31.0
Requires-Dist: requests-toolbelt ==1.0.0
Requires-Dist: six ==1.16.0
Requires-Dist: smmap ==5.0.1
Requires-Dist: tabulate ==0.9.0
Requires-Dist: treelib ==1.7.0
Requires-Dist: typing-extensions ==4.9.0
Requires-Dist: urllib3 ==2.2.0
